stockprophet_api/.DS_Store
stockprophet_api/__init__.py
stockprophet_api/app_factory.py
stockprophet_api/exceptions.py
stockprophet_api/math/calculator.py
stockprophet_api/math/monte_carlo.py
stockprophet_api/math/options_calculator.py
stockprophet_api/models/__init__.py
stockprophet_api/models/base_model.py
stockprophet_api/models/custom_types.py
stockprophet_api/models/equity_option.py
stockprophet_api/models/ohlcv.py
stockprophet_api/models/price.py
stockprophet_api/models/security.py
stockprophet_api/models/tick.py
stockprophet_api/models/tick_level.py
stockprophet_api/models/timeseries_data.py
stockprophet_api/models/trade.py
stockprophet_api/models/utils.py
stockprophet_api/routes/__init__.py
stockprophet_api/routes/equity_options.py
stockprophet_api/routes/securities.py
stockprophet_api/run.py
stockprophet_api/settings.py
stockprophet_api-0.1.0.dist-info/METADATA
stockprophet_api-0.1.0.dist-info/WHEEL
stockprophet_api-0.1.0.dist-info/RECORD
